{
  "updatedAt": "2026-02-13T15:53:03Z",
  "environments": {
    "alpha": {
      "status": "online",
      "code": 200,
      "checkedAt": "2026-02-13T15:53:03Z"
    },
    "beta": {
      "status": "online",
      "code": 200,
      "checkedAt": "2026-02-13T15:53:03Z"
    },
    "bpx": {
      "status": "online",
      "code": 200,
      "checkedAt": "2026-02-13T15:53:03Z"
    },
    "carlos": {
      "status": "online",
      "code": 200,
      "checkedAt": "2026-02-13T15:53:03Z"
    },
    "cenovus": {
      "status": "online",
      "code": 200,
      "checkedAt": "2026-02-13T15:53:03Z"
    },
    "clr": {
      "status": "online",
      "code": 200,
      "checkedAt": "2026-02-13T15:53:03Z"
    },
    "hal-cementing": {
      "status": "online",
      "code": 200,
      "checkedAt": "2026-02-13T15:53:03Z"
    },
    "hal-cementing-dev": {
      "status": "online",
      "code": 200,
      "checkedAt": "2026-02-13T15:53:03Z"
    },
    "hal-cementing-staging": {
      "status": "online",
      "code": 200,
      "checkedAt": "2026-02-13T15:53:03Z"
    },
    "hal-sandbox": {
      "status": "online",
      "code": 200,
      "checkedAt": "2026-02-13T15:53:03Z"
    },
    "hall-int-dev": {
      "status": "online",
      "code": 200,
      "checkedAt": "2026-02-13T15:53:03Z"
    },
    "hall-int-prod": {
      "status": "online",
      "code": 200,
      "checkedAt": "2026-02-13T15:53:03Z"
    },
    "halliburton-dev1": {
      "status": "online",
      "code": 200,
      "checkedAt": "2026-02-13T15:53:03Z"
    },
    "halliburton-prod1": {
      "status": "online",
      "code": 200,
      "checkedAt": "2026-02-13T15:53:03Z"
    },
    "idoba": {
      "status": "offline",
      "code": 503,
      "checkedAt": "2026-02-13T15:53:03Z"
    },
    "ironoak": {
      "status": "online",
      "code": 200,
      "checkedAt": "2026-02-13T15:53:03Z"
    },
    "ironoak-staging": {
      "status": "online",
      "code": 200,
      "checkedAt": "2026-02-13T15:53:03Z"
    },
    "jkmrc": {
      "status": "offline",
      "code": 503,
      "checkedAt": "2026-02-13T15:53:03Z"
    },
    "mcgx": {
      "status": "offline",
      "code": 503,
      "checkedAt": "2026-02-13T15:53:03Z"
    },
    "nuno": {
      "status": "online",
      "code": 200,
      "checkedAt": "2026-02-13T15:53:03Z"
    },
    "ovintiv": {
      "status": "offline",
      "code": 503,
      "checkedAt": "2026-02-13T15:53:03Z"
    },
    "petronas": {
      "status": "online",
      "code": 200,
      "checkedAt": "2026-02-13T15:53:03Z"
    },
    "qmai": {
      "status": "online",
      "code": 200,
      "checkedAt": "2026-02-13T15:53:03Z"
    },
    "sales": {
      "status": "online",
      "code": 200,
      "checkedAt": "2026-02-13T15:53:03Z"
    },
    "santos-cooper": {
      "status": "online",
      "code": 200,
      "checkedAt": "2026-02-13T15:53:03Z"
    },
    "santos-csg": {
      "status": "online",
      "code": 200,
      "checkedAt": "2026-02-13T15:53:03Z"
    },
    "santos-dev": {
      "status": "online",
      "code": 200,
      "checkedAt": "2026-02-13T15:53:03Z"
    },
    "santos-dev2": {
      "status": "online",
      "code": 200,
      "checkedAt": "2026-02-13T15:53:03Z"
    },
    "santos-staging": {
      "status": "online",
      "code": 200,
      "checkedAt": "2026-02-13T15:53:03Z"
    },
    "validus": {
      "status": "online",
      "code": 200,
      "checkedAt": "2026-02-13T15:53:03Z"
    },
    "westside": {
      "status": "online",
      "code": 200,
      "checkedAt": "2026-02-13T15:53:03Z"
    },
    "westside-staging": {
      "status": "online",
      "code": 200,
      "checkedAt": "2026-02-13T15:53:03Z"
    }
  }
}
