{
  "updatedAt": "2026-07-01T16:32:51Z",
  "environments": {
    "alpha": {
      "status": "online",
      "code": 200,
      "checkedAt": "2026-07-01T16:32:51Z"
    },
    "beta": {
      "status": "online",
      "code": 200,
      "checkedAt": "2026-07-01T16:32:51Z"
    },
    "bpx": {
      "status": "online",
      "code": 200,
      "checkedAt": "2026-07-01T16:32:51Z"
    },
    "cenovus": {
      "status": "online",
      "code": 200,
      "checkedAt": "2026-07-01T16:32:51Z"
    },
    "cenovus-staging": {
      "status": "online",
      "code": 200,
      "checkedAt": "2026-07-01T16:32:51Z"
    },
    "clr": {
      "status": "online",
      "code": 200,
      "checkedAt": "2026-07-01T16:32:51Z"
    },
    "diamondback": {
      "status": "online",
      "code": 200,
      "checkedAt": "2026-07-01T16:32:51Z"
    },
    "diamondback-staging": {
      "status": "online",
      "code": 200,
      "checkedAt": "2026-07-01T16:32:51Z"
    },
    "hal-cementing": {
      "status": "online",
      "code": 200,
      "checkedAt": "2026-07-01T16:32:51Z"
    },
    "hal-cementing-dev": {
      "status": "online",
      "code": 200,
      "checkedAt": "2026-07-01T16:32:51Z"
    },
    "hal-cementing-staging": {
      "status": "offline",
      "code": 0,
      "checkedAt": "2026-07-01T16:32:51Z"
    },
    "hal-sandbox": {
      "status": "online",
      "code": 200,
      "checkedAt": "2026-07-01T16:32:51Z"
    },
    "hall-int-dev": {
      "status": "online",
      "code": 200,
      "checkedAt": "2026-07-01T16:32:51Z"
    },
    "hall-int-prod": {
      "status": "online",
      "code": 200,
      "checkedAt": "2026-07-01T16:32:51Z"
    },
    "halliburton-dev1": {
      "status": "online",
      "code": 200,
      "checkedAt": "2026-07-01T16:32:51Z"
    },
    "halliburton-prod1": {
      "status": "online",
      "code": 200,
      "checkedAt": "2026-07-01T16:32:51Z"
    },
    "ironoak": {
      "status": "online",
      "code": 200,
      "checkedAt": "2026-07-01T16:32:51Z"
    },
    "ironoak-staging": {
      "status": "online",
      "code": 200,
      "checkedAt": "2026-07-01T16:32:51Z"
    },
    "messe": {
      "status": "online",
      "code": 200,
      "checkedAt": "2026-07-01T16:32:51Z"
    },
    "origin": {
      "status": "online",
      "code": 200,
      "checkedAt": "2026-07-01T16:32:51Z"
    },
    "propwr": {
      "status": "online",
      "code": 200,
      "checkedAt": "2026-07-01T16:32:51Z"
    },
    "propwr-dev": {
      "status": "online",
      "code": 200,
      "checkedAt": "2026-07-01T16:32:51Z"
    },
    "propwr-staging": {
      "status": "online",
      "code": 200,
      "checkedAt": "2026-07-01T16:32:51Z"
    },
    "qmai": {
      "status": "online",
      "code": 200,
      "checkedAt": "2026-07-01T16:32:51Z"
    },
    "sales": {
      "status": "online",
      "code": 200,
      "checkedAt": "2026-07-01T16:32:51Z"
    },
    "santos-cooper": {
      "status": "online",
      "code": 200,
      "checkedAt": "2026-07-01T16:32:51Z"
    },
    "santos-csg": {
      "status": "online",
      "code": 200,
      "checkedAt": "2026-07-01T16:32:51Z"
    },
    "santos-dev": {
      "status": "online",
      "code": 200,
      "checkedAt": "2026-07-01T16:32:51Z"
    },
    "santos-dev2": {
      "status": "online",
      "code": 200,
      "checkedAt": "2026-07-01T16:32:51Z"
    },
    "santos-staging": {
      "status": "online",
      "code": 200,
      "checkedAt": "2026-07-01T16:32:51Z"
    },
    "westside": {
      "status": "offline",
      "code": 503,
      "checkedAt": "2026-07-01T16:32:51Z"
    }
  }
}
